<annotation>
	<folder>있다-samples (1)</folder>
	<filename>120.jpg</filename>
	<path>D:\나현 프로젝트\dataset\있다\있다-samples (1)\120.jpg</path>
	<source>
		<database>Unknown</database>
	</source>
	<size>
		<width>224</width>
		<height>224</height>
		<depth>3</depth>
	</size>
	<segmented>0</segmented>
	<object>
		<name>HAVE</name>
		<pose>Unspecified</pose>
		<truncated>0</truncated>
		<difficult>0</difficult>
		<bndbox>
			<xmin>29</xmin>
			<ymin>19</ymin>
			<xmax>133</xmax>
			<ymax>145</ymax>
		</bndbox>
	</object>
</annotation>
