<annotation>
	<folder>집</folder>
	<filename>247_0.jpg</filename>
	<path>D:\나현 프로젝트\dataset\집\247_0.jpg</path>
	<source>
		<database>Unknown</database>
	</source>
	<size>
		<width>640</width>
		<height>480</height>
		<depth>3</depth>
	</size>
	<segmented>0</segmented>
	<object>
		<name>HOME</name>
		<pose>Unspecified</pose>
		<truncated>0</truncated>
		<difficult>0</difficult>
		<bndbox>
			<xmin>135</xmin>
			<ymin>217</ymin>
			<xmax>366</xmax>
			<ymax>376</ymax>
		</bndbox>
	</object>
</annotation>
